{"decodes":[{"freq_hz":0.0,"message":"CQ POTA KK4Z EM84","snr_db":0.0},{"freq_hz":0.0,"message":"N7WBV AD9GE EM69","snr_db":0.0},{"freq_hz":0.0,"message":"HG8LXL AD9P EN54","snr_db":0.0},{"freq_hz":0.0,"message":"KO3B N3LF EM66","snr_db":0.0},{"freq_hz":0.0,"message":"KO3B KC9NKI EM68","snr_db":0.0},{"freq_hz":0.0,"message":"AB8WW VE9NM -13","snr_db":0.0},{"freq_hz":0.0,"message":"CQ N4NDR EM85","snr_db":0.0},{"freq_hz":0.0,"message":"KO3B N5KKG EM51","snr_db":0.0},{"freq_hz":0.0,"message":"KO3B AC6SC DM14","snr_db":0.0},{"freq_hz":0.0,"message":"KC3VNB N1MC -02","snr_db":0.0},{"freq_hz":0.0,"message":"K0JV KF0VUJ 73","snr_db":0.0},{"freq_hz":0.0,"message":"K9HOU WB8UFC/P R+04","snr_db":0.0},{"freq_hz":0.0,"message":"MW3FLI K9PSR EN60","snr_db":0.0},{"freq_hz":0.0,"message":"CQ KA1MXL FN41","snr_db":0.0},{"freq_hz":0.0,"message":"VP2MAA KC0UDP EN31","snr_db":0.0},{"freq_hz":0.0,"message":"<...> KQ4NMU R-13","snr_db":0.0},{"freq_hz":0.0,"message":"KO3B K7FD CN74","snr_db":0.0},{"freq_hz":0.0,"message":"CQ POTA K4XP EM94","snr_db":0.0},{"freq_hz":0.0,"message":"KE8WVB W7DRO DM37","snr_db":0.0},{"freq_hz":0.0,"message":"CQ KD2YCK FN20","snr_db":0.0},{"freq_hz":0.0,"message":"KR4LAI KB9RP EN43","snr_db":0.0},{"freq_hz":0.0,"message":"CQ WA4TED EM75","snr_db":0.0},{"freq_hz":0.0,"message":"K4NSC AC9HP R-07","snr_db":0.0}],"schema_version":1,"source":"ft8_lib_ffi","wav_path":"/Users/thagale/.pancetta/recordings/ft8_20260530_165658.wav","wav_sha256":"0088818009e6758037a1b2cfaaa6e9c503050692924d5a659b7f32090c19e109"}