{"decodes":[{"freq_hz":0.0,"message":"CQ KF0SKV EN12","snr_db":0.0},{"freq_hz":0.0,"message":"CQ KN4DS EM82","snr_db":0.0},{"freq_hz":0.0,"message":"AC3KE AE6CH CM97","snr_db":0.0},{"freq_hz":0.0,"message":"XE3K WA8TJC EN80","snr_db":0.0},{"freq_hz":0.0,"message":"HI8L N4LOV R-09","snr_db":0.0},{"freq_hz":0.0,"message":"VA7ZT C6APS -15","snr_db":0.0},{"freq_hz":0.0,"message":"OH7MA NA9I EN51","snr_db":0.0},{"freq_hz":0.0,"message":"KM6SO WY7WL R-10","snr_db":0.0},{"freq_hz":0.0,"message":"CQ W5RWD EM26","snr_db":0.0},{"freq_hz":0.0,"message":"CQ KZ7K DM33","snr_db":0.0},{"freq_hz":0.0,"message":"K3HPA KE9ZZ RR73","snr_db":0.0},{"freq_hz":0.0,"message":"CQ AD9P EN54","snr_db":0.0},{"freq_hz":0.0,"message":"AC3KE WA4TED EM75","snr_db":0.0},{"freq_hz":0.0,"message":"CQ KG5VFJ EM20","snr_db":0.0},{"freq_hz":0.0,"message":"N1MRE W8KNX +00","snr_db":0.0},{"freq_hz":0.0,"message":"CQ CA6SNT FF30","snr_db":0.0}],"schema_version":1,"source":"ft8_lib_ffi","wav_path":"/Users/thagale/.pancetta/recordings/ft8_20260420_023743.wav","wav_sha256":"05c00738fc1ed663204edae94f9c7f174859bc08ea5d54cf8573e711dd69da53"}