{"decodes":[{"freq_hz":0.0,"message":"CQ POTA KN4RNO EM72","snr_db":0.0},{"freq_hz":0.0,"message":"KO4XJ KF7UGV DN61","snr_db":0.0},{"freq_hz":0.0,"message":"CQ KG4OJT FM18","snr_db":0.0},{"freq_hz":0.0,"message":"N0SNO KK7WBH DM42","snr_db":0.0},{"freq_hz":0.0,"message":"AC3LW W0NFS R-09","snr_db":0.0},{"freq_hz":0.0,"message":"AC3LW KQ4MYC EM65","snr_db":0.0},{"freq_hz":0.0,"message":"CQ AC4ZH EM78","snr_db":0.0},{"freq_hz":0.0,"message":"KR4DVQ KE9BDR +04","snr_db":0.0},{"freq_hz":0.0,"message":"XE2JT N8PLC EN32","snr_db":0.0},{"freq_hz":0.0,"message":"AC3LW KW8CW EM75","snr_db":0.0},{"freq_hz":0.0,"message":"M0ABG W1SBW FN33","snr_db":0.0},{"freq_hz":0.0,"message":"WB2AKH V31DL EK57","snr_db":0.0},{"freq_hz":0.0,"message":"CQ N4NDR EM85","snr_db":0.0},{"freq_hz":0.0,"message":"CQ W1SAV DM04","snr_db":0.0}],"schema_version":1,"source":"ft8_lib_ffi","wav_path":"/Users/thagale/.pancetta/recordings/ft8_20260530_181258.wav","wav_sha256":"05e5400120bd427f54c4538bc8f71ce3cd9293653fac36b90b5c28f0e9deb30f"}