{"decodes":[{"freq_hz":2540.625,"message":"CQ WZ0X EN26","snr_db":0.0,"time_sec":2.6399998664855957},{"freq_hz":500.0,"message":"VE6CB KG4OJT RR73","snr_db":0.0,"time_sec":2.799999952316284},{"freq_hz":1368.75,"message":"NG7E W7QQF 73","snr_db":0.0,"time_sec":2.799999952316284},{"freq_hz":1837.5,"message":"WA7YEJ N9RWG +00","snr_db":0.0,"time_sec":2.6399998664855957},{"freq_hz":2093.75,"message":"CQ AA4WX","snr_db":0.0,"time_sec":2.319999933242798},{"freq_hz":2737.5,"message":"EG1PCS KC3EIZ R-09","snr_db":0.0,"time_sec":3.119999885559082},{"freq_hz":221.875,"message":"CQ KD2WBX FN13","snr_db":0.0,"time_sec":2.319999933242798},{"freq_hz":2221.875,"message":"JY5JA AC2PB FN20","snr_db":0.0,"time_sec":3.0399999618530273},{"freq_hz":1506.25,"message":"K5DZY KK4ELM RR73","snr_db":0.0,"time_sec":1.8399999141693115},{"freq_hz":1700.0,"message":"WA5SWM W2EK RR73","snr_db":0.0,"time_sec":2.4800000190734863},{"freq_hz":2690.625,"message":"N2YW KM7FTZ DN05","snr_db":0.0,"time_sec":2.6399998664855957},{"freq_hz":2471.875,"message":"VA3GPL CE2EP -09","snr_db":0.0,"time_sec":2.879999876022339},{"freq_hz":2415.625,"message":"KC9YTT KI6GOA DM13","snr_db":0.0,"time_sec":2.6399998664855957},{"freq_hz":1921.875,"message":"IU0ERZ N3FMC -18","snr_db":0.0,"time_sec":2.6399998664855957},{"freq_hz":1868.75,"message":"WA7EEE K4VHE EM64","snr_db":0.0,"time_sec":2.6399998664855957},{"freq_hz":871.875,"message":"SV5BYP WB3FME -07","snr_db":0.0,"time_sec":2.559999942779541},{"freq_hz":659.375,"message":"CQ HI3RRR FK49","snr_db":0.0,"time_sec":1.8399999141693115},{"freq_hz":425.0,"message":"CE3TSK WD4AGF EL96","snr_db":0.0,"time_sec":2.7200000286102295},{"freq_hz":325.0,"message":"CQ WA4TED EM75","snr_db":0.0,"time_sec":2.6399998664855957},{"freq_hz":712.5,"message":"OK1UOZ KR4EOD RR73","snr_db":0.0,"time_sec":2.7200000286102295},{"freq_hz":1090.625,"message":"IS0KNG VE2ESF FN35","snr_db":0.0,"time_sec":2.6399998664855957},{"freq_hz":1768.75,"message":"TL8BNW KE4QEG EM70","snr_db":0.0,"time_sec":2.7200000286102295},{"freq_hz":2590.625,"message":"JY5JA K3RH FN20","snr_db":0.0,"time_sec":2.7200000286102295}],"schema_version":1,"source":"ft8_lib_ffi","wav_path":"/Users/thagale/.pancetta/recordings/ft8_20260530_230328.wav","wav_sha256":"1091967a8d3579a743ac6718289c90afeae267a8148fe6dd1ff6d68f696b8254"}