{"decodes":[{"freq_hz":1459.375,"message":"UK8GG YV6BXN -11","snr_db":0.0,"time_sec":2.879999876022339},{"freq_hz":2450.0,"message":"KQ4POB F4FWT RR73","snr_db":0.0,"time_sec":2.7200000286102295},{"freq_hz":2946.875,"message":"<...> K6VVP CM87","snr_db":0.0,"time_sec":2.879999876022339},{"freq_hz":690.625,"message":"CQ DX OZ3TT JO66","snr_db":0.0,"time_sec":2.879999876022339},{"freq_hz":2168.75,"message":"7X5CY W6SOL DN17","snr_db":0.0,"time_sec":2.799999952316284},{"freq_hz":1178.125,"message":"OH2ZZ VE7QCR R-03","snr_db":0.0,"time_sec":1.7599999904632568},{"freq_hz":875.0,"message":"<...> NI5L DM52","snr_db":0.0,"time_sec":2.7200000286102295},{"freq_hz":1796.875,"message":"CQ AG6X DM12","snr_db":0.0,"time_sec":2.7200000286102295},{"freq_hz":1062.5,"message":"7X5CY KL2GN BP51","snr_db":0.0,"time_sec":2.7200000286102295},{"freq_hz":1903.125,"message":"LZ1JZ WB7V DN13","snr_db":0.0,"time_sec":2.7200000286102295},{"freq_hz":2000.0,"message":"<...> KD3ANN R+00","snr_db":0.0,"time_sec":2.799999952316284},{"freq_hz":2725.0,"message":"CQ KH6DC BL11","snr_db":0.0,"time_sec":2.9600000381469727},{"freq_hz":2668.75,"message":"CN8NS N6RW 73","snr_db":0.0,"time_sec":2.7200000286102295},{"freq_hz":146.875,"message":"UT1XU AI0Y -02","snr_db":0.0,"time_sec":2.9600000381469727},{"freq_hz":240.625,"message":"KB3DQI R3UG -16","snr_db":0.0,"time_sec":3.119999885559082},{"freq_hz":2275.0,"message":"KG7LBW F5PBG R-14","snr_db":0.0,"time_sec":2.4800000190734863},{"freq_hz":343.75,"message":"CQ NA UR3CFC KN58","snr_db":0.0,"time_sec":2.7200000286102295},{"freq_hz":2500.0,"message":"KS7T AJ6TL DM03","snr_db":0.0,"time_sec":2.7200000286102295},{"freq_hz":481.25,"message":"CQ N6MCW CM98","snr_db":0.0,"time_sec":2.6399998664855957},{"freq_hz":1393.75,"message":"N7LRG NL8F +17","snr_db":0.0,"time_sec":2.7200000286102295},{"freq_hz":1637.5,"message":"VE4ZIM RW9AW/P 73","snr_db":0.0,"time_sec":2.799999952316284},{"freq_hz":2768.75,"message":"CN8NS AD6KH CM95","snr_db":0.0,"time_sec":2.799999952316284}],"schema_version":1,"source":"ft8_lib_ffi","wav_path":"/Users/thagale/.pancetta/recordings/ft8_20260428_032628.wav","wav_sha256":"19f53ad760bc00df052dc809dff26c6d648f887277242444a3839efb233e5789"}