{"decodes":[{"freq_hz":0.0,"message":"SV9MBH KJ4GNR EL95","snr_db":0.0},{"freq_hz":0.0,"message":"N4VEG KZ7Y RR73","snr_db":0.0},{"freq_hz":0.0,"message":"CQ EU VA7QI CO70","snr_db":0.0},{"freq_hz":0.0,"message":"LZ1SJ KF9UG EN71","snr_db":0.0},{"freq_hz":0.0,"message":"W5XO W3LEL R-05","snr_db":0.0},{"freq_hz":0.0,"message":"CQ AD9DU EN52","snr_db":0.0},{"freq_hz":0.0,"message":"CQ NP3KW FK78","snr_db":0.0},{"freq_hz":0.0,"message":"AD9GL N8PFK 73","snr_db":0.0},{"freq_hz":0.0,"message":"LZ9DX KQ4NAQ EM93","snr_db":0.0},{"freq_hz":0.0,"message":"W7BA WA4Q R-04","snr_db":0.0},{"freq_hz":0.0,"message":"CQ AI5YU EM13","snr_db":0.0},{"freq_hz":0.0,"message":"WD6DKW N2LCX FN13","snr_db":0.0},{"freq_hz":0.0,"message":"VE3PFW KG7IXX R-13","snr_db":0.0},{"freq_hz":0.0,"message":"W6JZ IQ4JO 73","snr_db":0.0},{"freq_hz":0.0,"message":"N7PWZ I1RJP JN45","snr_db":0.0},{"freq_hz":0.0,"message":"CQ WW3QB FM28","snr_db":0.0},{"freq_hz":0.0,"message":"SP3HIF RU3DX R-13","snr_db":0.0}],"schema_version":1,"source":"ft8_lib_ffi","wav_path":"/Users/thagale/.pancetta/recordings/ft8_20260424_030058.wav","wav_sha256":"211f5a521f6568a6b9269fadc203fd05f7db43874114c4d220a3971f99e48cc7"}