{"decodes":[{"freq_hz":328.125,"message":"CQ WA4TED EM75","snr_db":0.0,"time_sec":2.6399998664855957},{"freq_hz":590.625,"message":"K4NKU K2PS +00","snr_db":0.0,"time_sec":2.7200000286102295},{"freq_hz":2590.625,"message":"RA4AHN K3RH FN20","snr_db":0.0,"time_sec":2.7200000286102295},{"freq_hz":1115.625,"message":"VA6VZ WA7YZW 73","snr_db":0.0,"time_sec":2.7200000286102295},{"freq_hz":1975.0,"message":"SV2IQC V31DL EK57","snr_db":0.0,"time_sec":2.799999952316284},{"freq_hz":500.0,"message":"CQ KG4OJT FM18","snr_db":0.0,"time_sec":2.799999952316284},{"freq_hz":2284.375,"message":"VA7GEM KF5YRQ EM46","snr_db":0.0,"time_sec":2.799999952316284},{"freq_hz":1859.375,"message":"UX0ZAB KD2YQS -16","snr_db":0.0,"time_sec":2.7200000286102295},{"freq_hz":975.0,"message":"DM1YS KF8BRC -20","snr_db":0.0,"time_sec":2.7200000286102295},{"freq_hz":1378.125,"message":"WB3W KD0QPC EM38","snr_db":0.0,"time_sec":2.6399998664855957},{"freq_hz":846.875,"message":"KL7FDQ KW6AE RR73","snr_db":0.0,"time_sec":2.799999952316284},{"freq_hz":2381.25,"message":"N5YDX KF9UG -01","snr_db":0.0,"time_sec":2.6399998664855957},{"freq_hz":1278.125,"message":"ZB2MR WA2SI FN30","snr_db":0.0,"time_sec":2.799999952316284},{"freq_hz":2643.75,"message":"HK0RMR KG4RWO R+09","snr_db":0.0,"time_sec":2.7200000286102295},{"freq_hz":2459.375,"message":"HK0RMR K7CTV DM42","snr_db":0.0,"time_sec":2.799999952316284},{"freq_hz":2128.125,"message":"CQ 9A5E JN75","snr_db":0.0,"time_sec":2.7200000286102295},{"freq_hz":2062.5,"message":"HB9OAB N4EMG RR73","snr_db":0.0,"time_sec":2.7200000286102295},{"freq_hz":746.875,"message":"TA4DX K4VHE EM64","snr_db":0.0,"time_sec":2.7200000286102295},{"freq_hz":1050.0,"message":"KF8EFV S55DX 73","snr_db":0.0,"time_sec":2.879999876022339},{"freq_hz":1246.875,"message":"CQ K4SYT EM90","snr_db":0.0,"time_sec":2.6399998664855957}],"schema_version":1,"source":"ft8_lib_ffi","wav_path":"/Users/thagale/.pancetta/recordings/ft8_20260530_220028.wav","wav_sha256":"2a15822c28be7eaae7ad2844bcd60e21e5bf8500e1933fa7a9b0053436914ecc"}