{"decodes":[{"freq_hz":0.0,"message":"RN6HGI KA2MGE R-04","snr_db":0.0},{"freq_hz":0.0,"message":"UN7BCF NY9H -07","snr_db":0.0},{"freq_hz":0.0,"message":"EC3A KJ7WFN -16","snr_db":0.0},{"freq_hz":0.0,"message":"N6BLU K3FH EN90","snr_db":0.0},{"freq_hz":0.0,"message":"EW6AS K7SP DM33","snr_db":0.0},{"freq_hz":0.0,"message":"UA8Q N2YW RR73","snr_db":0.0},{"freq_hz":0.0,"message":"<...> K2TQC -07","snr_db":0.0},{"freq_hz":0.0,"message":"IT9KHP VA7ZM CN89","snr_db":0.0},{"freq_hz":0.0,"message":"RW9WT KK7MJD RR73","snr_db":0.0},{"freq_hz":0.0,"message":"CQ OH2XO KP20","snr_db":0.0},{"freq_hz":0.0,"message":"CT1BFP KD3ACB -08","snr_db":0.0},{"freq_hz":0.0,"message":"EU6AF W7UDH -05","snr_db":0.0},{"freq_hz":0.0,"message":"7X5CY W4IDX DM24","snr_db":0.0},{"freq_hz":0.0,"message":"KO6DGB KZ7K RR73","snr_db":0.0},{"freq_hz":0.0,"message":"KF5NQV WS4ASE RR73","snr_db":0.0},{"freq_hz":0.0,"message":"7X5CY KG8DH EM89","snr_db":0.0},{"freq_hz":0.0,"message":"CQ UN7EAX MO52","snr_db":0.0},{"freq_hz":0.0,"message":"W7KK RW4C RR73","snr_db":0.0}],"schema_version":1,"source":"ft8_lib_ffi","wav_path":"/Users/thagale/.pancetta/recordings/ft8_20260428_025128.wav","wav_sha256":"3fa6faa49657c7ae49584a3f1a26ccd55482b3343013bd23b90f210feae28013"}