{"decodes":[{"freq_hz":2018.75,"message":"AC3LW W9AV EN43","snr_db":0.0,"time_sec":2.879999876022339},{"freq_hz":2387.5,"message":"KO4DUL KB9DED EN54","snr_db":0.0,"time_sec":2.6399998664855957},{"freq_hz":2296.875,"message":"W8DGZ K8USN EM90","snr_db":0.0,"time_sec":2.799999952316284},{"freq_hz":690.625,"message":"CQ KQ4YIF EM17","snr_db":0.0,"time_sec":2.9600000381469727},{"freq_hz":1253.125,"message":"N5BK N4NDR +07","snr_db":0.0,"time_sec":2.7200000286102295},{"freq_hz":2846.875,"message":"WA9TT KF7UGV DN61","snr_db":0.0,"time_sec":2.799999952316284},{"freq_hz":1112.5,"message":"K6KWI N2TKL EM74","snr_db":0.0,"time_sec":2.7200000286102295},{"freq_hz":868.75,"message":"KI7HLO KF9UG EN71","snr_db":0.0,"time_sec":2.7200000286102295},{"freq_hz":428.125,"message":"KD2VRL WD4AGF R-14","snr_db":0.0,"time_sec":2.799999952316284},{"freq_hz":1496.875,"message":"CQ W7CTY EM69","snr_db":0.0,"time_sec":2.7200000286102295},{"freq_hz":1012.5,"message":"SV9KNA KB9SJD EN43","snr_db":0.0,"time_sec":2.7200000286102295},{"freq_hz":328.125,"message":"CQ WA4TED EM75","snr_db":0.0,"time_sec":2.7200000286102295},{"freq_hz":359.375,"message":"W4FYB KA0FMZ -08","snr_db":0.0,"time_sec":2.6399998664855957},{"freq_hz":2756.25,"message":"DL1NCH AC4ZH -16","snr_db":0.0,"time_sec":2.9600000381469727}],"schema_version":1,"source":"ft8_lib_ffi","wav_path":"/Users/thagale/.pancetta/recordings/ft8_20260530_182058.wav","wav_sha256":"463f754d018ae1096338204bdf39eeb9cb30677950bf2e84615d54c4999df586"}