{"decodes":[{"freq_hz":0.0,"message":"SX1FLY KE9AVF EM78","snr_db":0.0},{"freq_hz":0.0,"message":"SV9KNA K4VHE EM64","snr_db":0.0},{"freq_hz":0.0,"message":"SV9KNA KQ4KKU EM72","snr_db":0.0},{"freq_hz":0.0,"message":"<...> VE3XN EN93","snr_db":0.0},{"freq_hz":0.0,"message":"KI5MQY WA4FU -06","snr_db":0.0},{"freq_hz":0.0,"message":"EG1PCS KF9UG R-09","snr_db":0.0},{"freq_hz":0.0,"message":"KC1FNM KQ4AIF -07","snr_db":0.0},{"freq_hz":0.0,"message":"CQ KG4OJT FM18","snr_db":0.0},{"freq_hz":0.0,"message":"CQ W8JDP EM79","snr_db":0.0},{"freq_hz":0.0,"message":"7Z1IS K3RH FN20","snr_db":0.0},{"freq_hz":0.0,"message":"K5MGY N3TOY -11","snr_db":0.0},{"freq_hz":0.0,"message":"V31ZA AC2PB FN20","snr_db":0.0},{"freq_hz":0.0,"message":"KC1FNM W9AV EN43","snr_db":0.0},{"freq_hz":0.0,"message":"KJ7BJS K0MDS EM38","snr_db":0.0},{"freq_hz":0.0,"message":"W4SFD N7MDW R-20","snr_db":0.0},{"freq_hz":0.0,"message":"V31ZA KA4HVL EM70","snr_db":0.0},{"freq_hz":0.0,"message":"PY2BS N2FBV FN30","snr_db":0.0},{"freq_hz":0.0,"message":"CQ WA4TED EM75","snr_db":0.0},{"freq_hz":0.0,"message":"OK1UOZ K4ZH -15","snr_db":0.0},{"freq_hz":0.0,"message":"KF0U WZ3D R+03","snr_db":0.0},{"freq_hz":0.0,"message":"CQ NP3DM FK68","snr_db":0.0},{"freq_hz":0.0,"message":"HK0RMR N6ZDH CM97","snr_db":0.0}],"schema_version":1,"source":"ft8_lib_ffi","wav_path":"/Users/thagale/.pancetta/recordings/ft8_20260530_205858.wav","wav_sha256":"4f1106713296dc9758245ac26024fe2fc95d21f373efb2fb451d562d38cdf664"}