{"decodes":[{"freq_hz":834.375,"message":"W4PRK N9RDX EN70","snr_db":0.0,"time_sec":2.7200000286102295},{"freq_hz":984.375,"message":"VA7JH WB4RRD EM73","snr_db":0.0,"time_sec":2.7200000286102295},{"freq_hz":2521.875,"message":"W4PRK K8SJM EM79","snr_db":0.0,"time_sec":2.799999952316284},{"freq_hz":1056.25,"message":"K7JWY AD9GE R-16","snr_db":0.0,"time_sec":2.7200000286102295},{"freq_hz":2250.0,"message":"PD5MVH KA7RAS EM80","snr_db":0.0,"time_sec":2.7200000286102295},{"freq_hz":1893.75,"message":"W4PRK KO3F FM19","snr_db":0.0,"time_sec":2.7200000286102295},{"freq_hz":581.25,"message":"CQ W4VBK EL98","snr_db":0.0,"time_sec":2.1599998474121094},{"freq_hz":1246.875,"message":"XE2AKL K4SYT -15","snr_db":0.0,"time_sec":2.7200000286102295},{"freq_hz":756.25,"message":"KJ4EB KI2D R-11","snr_db":0.0,"time_sec":2.9600000381469727},{"freq_hz":2415.625,"message":"CQ K4OP EM77","snr_db":0.0,"time_sec":2.3999998569488525},{"freq_hz":328.125,"message":"CQ WA4TED EM75","snr_db":0.0,"time_sec":2.799999952316284},{"freq_hz":1793.75,"message":"K0FO W9RTF +01","snr_db":0.0,"time_sec":2.319999933242798},{"freq_hz":2828.125,"message":"W6TJK VA7GEM RR73","snr_db":0.0,"time_sec":2.7200000286102295},{"freq_hz":1971.875,"message":"SP6DT V31DL EK57","snr_db":0.0,"time_sec":2.799999952316284},{"freq_hz":2296.875,"message":"KF8EBV N0CLS RRR","snr_db":0.0,"time_sec":2.7200000286102295},{"freq_hz":384.375,"message":"N1NRL IK4LZH JN54","snr_db":0.0,"time_sec":2.799999952316284},{"freq_hz":1400.0,"message":"K6JFR K5NWZ R-06","snr_db":0.0,"time_sec":2.7200000286102295},{"freq_hz":659.375,"message":"KZ4GN KQ4MYC EM65","snr_db":0.0,"time_sec":2.7200000286102295}],"schema_version":1,"source":"ft8_lib_ffi","wav_path":"/Users/thagale/.pancetta/recordings/ft8_20260530_192428.wav","wav_sha256":"587d7ae960115972157ef9b052d09ed4d3ef21d5190a09b97ed6bb8da5634812"}