{"decodes":[{"freq_hz":0.0,"message":"KO3B N3LF EM66","snr_db":0.0},{"freq_hz":0.0,"message":"K0JV KF0VUJ R-16","snr_db":0.0},{"freq_hz":0.0,"message":"SV9KNA K4LDC EM74","snr_db":0.0},{"freq_hz":0.0,"message":"N7WBV AD9GE EM69","snr_db":0.0},{"freq_hz":0.0,"message":"KO3B N5KKG EM51","snr_db":0.0},{"freq_hz":0.0,"message":"CQ VE9NM FN65","snr_db":0.0},{"freq_hz":0.0,"message":"N1NRL N1MC -09","snr_db":0.0},{"freq_hz":0.0,"message":"K9HOU WB8UFC/P R+02","snr_db":0.0},{"freq_hz":0.0,"message":"K1WOR WW4HG EM93","snr_db":0.0},{"freq_hz":0.0,"message":"KO3B W3ACO EN41","snr_db":0.0},{"freq_hz":0.0,"message":"CQ N4NDR EM85","snr_db":0.0},{"freq_hz":0.0,"message":"<...> KQ4NMU R-17","snr_db":0.0},{"freq_hz":0.0,"message":"VA5KEN AD9P 73","snr_db":0.0},{"freq_hz":0.0,"message":"KR4LAI K7CTV DM42","snr_db":0.0},{"freq_hz":0.0,"message":"WL7AUV WA4TED -16","snr_db":0.0},{"freq_hz":0.0,"message":"CQ K1GUY FN42","snr_db":0.0},{"freq_hz":0.0,"message":"KA8HNS KB9RP EN43","snr_db":0.0},{"freq_hz":0.0,"message":"K8YE N4SFC EL98","snr_db":0.0},{"freq_hz":0.0,"message":"KO3B KN6KI CN80","snr_db":0.0},{"freq_hz":0.0,"message":"KO3B AB9GK EN54","snr_db":0.0}],"schema_version":1,"source":"ft8_lib_ffi","wav_path":"/Users/thagale/.pancetta/recordings/ft8_20260530_165458.wav","wav_sha256":"6e56b3bf204d4b2a0976e63934b4ff41611bbb516dccab73f0af72b178dcb7b1"}