{"decodes":[{"freq_hz":0.0,"message":"WA9TT KJ4V EM74","snr_db":0.0},{"freq_hz":0.0,"message":"KV1F KN4RNO 73","snr_db":0.0},{"freq_hz":0.0,"message":"N8PLC KC8MLB R+04","snr_db":0.0},{"freq_hz":0.0,"message":"KS4NG WA0TDA -16","snr_db":0.0},{"freq_hz":0.0,"message":"KC6SKM K7CTV 73","snr_db":0.0},{"freq_hz":0.0,"message":"<...> KF9UG EN71","snr_db":0.0},{"freq_hz":0.0,"message":"CQ W4UTZ EM95","snr_db":0.0},{"freq_hz":0.0,"message":"CQ N4NDR EM85","snr_db":0.0},{"freq_hz":0.0,"message":"KO4XJ KF7UGV DN61","snr_db":0.0},{"freq_hz":0.0,"message":"WN9K HI3QMT -15","snr_db":0.0},{"freq_hz":0.0,"message":"CQ POTA KO4XJ EM57","snr_db":0.0},{"freq_hz":0.0,"message":"KO3B W0NFS EM48","snr_db":0.0},{"freq_hz":0.0,"message":"VA7LWK KK4ELM -20","snr_db":0.0},{"freq_hz":0.0,"message":"CQ KG4OJT FM18","snr_db":0.0},{"freq_hz":0.0,"message":"CQ AC4ZH EM78","snr_db":0.0},{"freq_hz":0.0,"message":"KJ5LMM W0ABE +09","snr_db":0.0},{"freq_hz":0.0,"message":"N5CPC V31DL EK57","snr_db":0.0},{"freq_hz":0.0,"message":"CQ VE3KRP EN58","snr_db":0.0},{"freq_hz":0.0,"message":"CQ WA4TED EM75","snr_db":0.0},{"freq_hz":0.0,"message":"N3HCN AC7WY DN61","snr_db":0.0}],"schema_version":1,"source":"ft8_lib_ffi","wav_path":"/Users/thagale/.pancetta/recordings/ft8_20260530_181528.wav","wav_sha256":"70dbe71b2aecc5ff192d4bfcc8604ccf12facff43b480916172cf9286bfcd43b"}