{"decodes":[{"freq_hz":2221.875,"message":"VC9UN AC2PB FN20","snr_db":0.0,"time_sec":2.7200000286102295},{"freq_hz":1984.375,"message":"EG8DDC KK4RXE EM75","snr_db":0.0,"time_sec":2.9600000381469727},{"freq_hz":2415.625,"message":"CQ KC9YTT EN40","snr_db":0.0,"time_sec":2.7200000286102295},{"freq_hz":1243.75,"message":"EG8DDC KD8JM EN82","snr_db":0.0,"time_sec":2.799999952316284},{"freq_hz":356.25,"message":"CQ K8BL EN91","snr_db":0.0,"time_sec":2.7200000286102295},{"freq_hz":1368.75,"message":"KA7RAS NG7E -12","snr_db":0.0,"time_sec":2.9600000381469727},{"freq_hz":1050.0,"message":"KF4VTT W5LGA DM65","snr_db":0.0,"time_sec":2.7200000286102295},{"freq_hz":2687.5,"message":"A92AE AE1AA FN43","snr_db":0.0,"time_sec":2.799999952316284},{"freq_hz":1581.25,"message":"7Z1CE KI4RFN EM91","snr_db":0.0,"time_sec":2.7200000286102295},{"freq_hz":712.5,"message":"EA6AOD KR4EOD R-01","snr_db":0.0,"time_sec":2.799999952316284},{"freq_hz":2028.125,"message":"AC9HP N3TOY -19","snr_db":0.0,"time_sec":2.879999876022339},{"freq_hz":2100.0,"message":"K1JLB NS7U R-01","snr_db":0.0,"time_sec":2.6399998664855957},{"freq_hz":2746.875,"message":"K1JLB N2YW +00","snr_db":0.0,"time_sec":2.6399998664855957},{"freq_hz":650.0,"message":"CQ VE3VSA EN83","snr_db":0.0,"time_sec":2.799999952316284},{"freq_hz":996.875,"message":"A92AE WV1W -07","snr_db":0.0,"time_sec":2.9600000381469727},{"freq_hz":1478.125,"message":"A92AE YV4AW FK50","snr_db":0.0,"time_sec":2.6399998664855957},{"freq_hz":2862.5,"message":"HH2JR WY4M EM78","snr_db":0.0,"time_sec":3.119999885559082},{"freq_hz":1753.125,"message":"EG8DDC VE3XN EN93","snr_db":0.0,"time_sec":2.799999952316284}],"schema_version":1,"source":"ft8_lib_ffi","wav_path":"/Users/thagale/.pancetta/recordings/ft8_20260530_225713.wav","wav_sha256":"747e12faf4c0fd10a9f2ec1d2e204d31ded381c66e9d3158f71798b2561506a3"}