{"decodes":[{"freq_hz":2659.375,"message":"CQ KO6MFA CM94","snr_db":0.0,"time_sec":2.799999952316284},{"freq_hz":565.625,"message":"CQ KE8ESJ EM79","snr_db":0.0,"time_sec":2.7200000286102295},{"freq_hz":187.5,"message":"KO1U W0JLR -12","snr_db":0.0,"time_sec":2.0},{"freq_hz":2284.375,"message":"<...> W4LAB +02","snr_db":0.0,"time_sec":2.3999998569488525},{"freq_hz":525.0,"message":"VE6CV KB9RP RRR","snr_db":0.0,"time_sec":0.3999999761581421},{"freq_hz":1756.25,"message":"CQ N5VAN DN91","snr_db":0.0,"time_sec":2.6399998664855957},{"freq_hz":1321.875,"message":"K7FD WZ8DX R-11","snr_db":0.0,"time_sec":2.7200000286102295},{"freq_hz":862.5,"message":"M1DDD/P KE2ET EM75","snr_db":0.0,"time_sec":2.9600000381469727},{"freq_hz":1625.0,"message":"KN4RNO WB0PTD EM28","snr_db":0.0,"time_sec":2.240000009536743},{"freq_hz":1046.875,"message":"CQ W1AW/0","snr_db":0.0,"time_sec":2.7200000286102295},{"freq_hz":1790.625,"message":"KN4RNO KE0QEQ EN04","snr_db":0.0,"time_sec":2.4800000190734863},{"freq_hz":2065.625,"message":"RC9A W1CCO FN43","snr_db":0.0,"time_sec":2.799999952316284},{"freq_hz":2475.0,"message":"VA3WL N0SMX 73","snr_db":0.0,"time_sec":2.3999998569488525},{"freq_hz":1368.75,"message":"9A2AA NG7E R-14","snr_db":0.0,"time_sec":2.9600000381469727},{"freq_hz":1471.875,"message":"W4NEL N4DWD EM86","snr_db":0.0,"time_sec":2.7200000286102295},{"freq_hz":2537.5,"message":"KF4VTT KD9PML RR73","snr_db":0.0,"time_sec":2.7200000286102295},{"freq_hz":1159.375,"message":"N1KLM HK3W FJ34","snr_db":0.0,"time_sec":2.7200000286102295},{"freq_hz":2743.75,"message":"WB6MPH KK7O DM43","snr_db":0.0,"time_sec":2.879999876022339},{"freq_hz":800.0,"message":"RG2V WI1U R-06","snr_db":0.0,"time_sec":2.4800000190734863},{"freq_hz":2137.5,"message":"KA3FMO KN4VTX -12","snr_db":0.0,"time_sec":2.879999876022339},{"freq_hz":2190.625,"message":"CQ KE9CK EN60","snr_db":0.0,"time_sec":2.7200000286102295}],"schema_version":1,"source":"ft8_lib_ffi","wav_path":"/Users/thagale/.pancetta/recordings/ft8_20260530_154813.wav","wav_sha256":"77f5c6a72df091f17c83f33d9ffd7d5d730655bbc718ab97db5641f5ac1619b5"}