{
  "schema_version": 1,
  "wav_path": "/Users/thagale/.pancetta/recordings/ft8_20260530_215743.wav",
  "wav_sha256": "83ac2ecb5e7d6446eac65327f4da6526c3ceff525e127244930681248ef9ebcc",
  "decoder_identity": "jt9 (/Applications/wsjtx.app/Contents/MacOS/jt9)",
  "decodes": [
    {
      "message": "E75T K3LL -05",
      "freq_hz": 1494.0,
      "dt_s": 2.0,
      "snr_db": 1.0
    },
    {
      "message": "VA7GEM W6GOK",
      "freq_hz": 2837.0,
      "dt_s": 2.1,
      "snr_db": 18.0
    },
    {
      "message": "IK4LZH KC0VTJ -17",
      "freq_hz": 1104.0,
      "dt_s": 2.1,
      "snr_db": 1.0
    },
    {
      "message": "CQ K8BL EN91",
      "freq_hz": 357.0,
      "dt_s": 2.0,
      "snr_db": -4.0
    },
    {
      "message": "9A5E K4WDW 73",
      "freq_hz": 847.0,
      "dt_s": 2.3,
      "snr_db": -12.0
    },
    {
      "message": "IK4LZH K0JHW EM17",
      "freq_hz": 1579.0,
      "dt_s": 2.2,
      "snr_db": -8.0
    },
    {
      "message": "KO1U K4NKU RR73",
      "freq_hz": 1040.0,
      "dt_s": 0.2,
      "snr_db": 9.0
    },
    {
      "message": "NI7L VE3GLN R-18",
      "freq_hz": 2359.0,
      "dt_s": 1.8,
      "snr_db": 6.0
    },
    {
      "message": "HH2JR KB0UZT EN34",
      "freq_hz": 2562.0,
      "dt_s": 2.0,
      "snr_db": -1.0
    },
    {
      "message": "KK7HSO KA6PYE EM66",
      "freq_hz": 1683.0,
      "dt_s": 2.0,
      "snr_db": 4.0
    },
    {
      "message": "A61CK W3BL FN20",
      "freq_hz": 1288.0,
      "dt_s": 2.1,
      "snr_db": 2.0
    },
    {
      "message": "ON4WIY KF8EFV RR73",
      "freq_hz": 1893.0,
      "dt_s": 2.2,
      "snr_db": -13.0
    },
    {
      "message": "WB4VMX K7CTV DM42",
      "freq_hz": 2458.0,
      "dt_s": 2.1,
      "snr_db": -13.0
    },
    {
      "message": "K3UCQ KO4XJ +00",
      "freq_hz": 2149.0,
      "dt_s": 2.0,
      "snr_db": -15.0
    },
    {
      "message": "W4NEL KE8UCE 73",
      "freq_hz": 2101.0,
      "dt_s": 2.0,
      "snr_db": -19.0
    },
    {
      "message": "CQ KZ4GN EL98",
      "freq_hz": 1981.0,
      "dt_s": 2.3,
      "snr_db": -3.0
    },
    {
      "message": "KD0QPC AE6ML -19",
      "freq_hz": 789.0,
      "dt_s": 2.1,
      "snr_db": -14.0
    },
    {
      "message": "IS0KNG KN4IWD EM75",
      "freq_hz": 2917.0,
      "dt_s": 2.0,
      "snr_db": -2.0
    },
    {
      "message": "CQ W4FN EM63",
      "freq_hz": 1365.0,
      "dt_s": 2.0,
      "snr_db": 1.0
    },
    {
      "message": "WB4VMX F5RRS 73",
      "freq_hz": 930.0,
      "dt_s": 2.2,
      "snr_db": -22.0
    },
    {
      "message": "KE8WVB AE4M EM64",
      "freq_hz": 1315.0,
      "dt_s": 2.0,
      "snr_db": -2.0
    },
    {
      "message": "IS0KNG N3PK EM84",
      "freq_hz": 706.0,
      "dt_s": 2.0,
      "snr_db": -7.0
    },
    {
      "message": "IZ0BYM AC7WY DN61",
      "freq_hz": 2268.0,
      "dt_s": 2.1,
      "snr_db": -24.0
    },
    {
      "message": "IZ0VZS KE2GJN -15",
      "freq_hz": 662.0,
      "dt_s": 2.2,
      "snr_db": -12.0
    },
    {
      "message": "F1HFP WA2SI -25",
      "freq_hz": 1277.0,
      "dt_s": 2.0,
      "snr_db": -8.0
    },
    {
      "message": "KL7FDQ NG7E -14",
      "freq_hz": 1369.0,
      "dt_s": 2.2,
      "snr_db": -6.0
    },
    {
      "message": "KC1OT KE8ZXF EN63",
      "freq_hz": 1109.0,
      "dt_s": 2.1,
      "snr_db": -10.0
    },
    {
      "message": "CQ KC9RAX EN70",
      "freq_hz": 869.0,
      "dt_s": 2.0,
      "snr_db": -22.0
    },
    {
      "message": "HH2JR KE8ESJ R-08",
      "freq_hz": 2381.0,
      "dt_s": 2.0,
      "snr_db": -5.0
    },
    {
      "message": "NI7L VA5KEN DO70",
      "freq_hz": 1806.0,
      "dt_s": 2.1,
      "snr_db": -25.0
    },
    {
      "message": "CQ KC9YTT EN40",
      "freq_hz": 2416.0,
      "dt_s": 2.0,
      "snr_db": -11.0
    },
    {
      "message": "CQ K8ZA EN80",
      "freq_hz": 1376.0,
      "dt_s": 2.2,
      "snr_db": -10.0
    },
    {
      "message": "IK0JXO KB2ELA -20",
      "freq_hz": 600.0,
      "dt_s": 2.1,
      "snr_db": -5.0
    },
    {
      "message": "KB2KBC AD6GO DM33",
      "freq_hz": 1331.0,
      "dt_s": 2.0,
      "snr_db": -13.0
    },
    {
      "message": "KG4SYK N5VAN -11",
      "freq_hz": 1757.0,
      "dt_s": 1.9,
      "snr_db": -15.0
    },
    {
      "message": "N1EDF K9YQ EN61",
      "freq_hz": 2293.0,
      "dt_s": 1.7,
      "snr_db": -20.0
    },
    {
      "message": "DD1UN VE3HA FN03",
      "freq_hz": 1165.0,
      "dt_s": 2.1,
      "snr_db": -23.0
    },
    {
      "message": "NI7L AF0FX R-05",
      "freq_hz": 1163.0,
      "dt_s": 2.2,
      "snr_db": -25.0
    },
    {
      "message": "CQ KD0XD EN12",
      "freq_hz": 1756.0,
      "dt_s": 2.0,
      "snr_db": -19.0
    },
    {
      "message": "KF5YRQ W0ABE RR73",
      "freq_hz": 2523.0,
      "dt_s": 2.4,
      "snr_db": -25.0
    }
  ],
  "elapsed_seconds": 7.98792075
}