{"decodes":[{"freq_hz":0.0,"message":"KC3HRV K4LDC R-11","snr_db":0.0},{"freq_hz":0.0,"message":"CQ KC9YTT EN40","snr_db":0.0},{"freq_hz":0.0,"message":"BD7KWU KN6WEV CM97","snr_db":0.0},{"freq_hz":0.0,"message":"CQ N1ET FN41","snr_db":0.0},{"freq_hz":0.0,"message":"G0VXM K0MDS EM38","snr_db":0.0},{"freq_hz":0.0,"message":"VA3EWV K0JV DN84","snr_db":0.0},{"freq_hz":0.0,"message":"WH6S KC9NKI R+05","snr_db":0.0},{"freq_hz":0.0,"message":"WW4HG K7CTV DM42","snr_db":0.0},{"freq_hz":0.0,"message":"AA0MZ AI4JD -19","snr_db":0.0},{"freq_hz":0.0,"message":"CQ POTA KO3B DN70","snr_db":0.0},{"freq_hz":0.0,"message":"W4NEL KF0MAU EN35","snr_db":0.0},{"freq_hz":0.0,"message":"KO6BFR NG7E RR73","snr_db":0.0},{"freq_hz":0.0,"message":"K5MGY KR4LAI -12","snr_db":0.0},{"freq_hz":0.0,"message":"KQ4NMU <...> -10","snr_db":0.0},{"freq_hz":0.0,"message":"VA3EWV KE8IFR EM79","snr_db":0.0},{"freq_hz":0.0,"message":"W4SIJ W9AKS R-12","snr_db":0.0},{"freq_hz":0.0,"message":"CQ KZ4GN EL98","snr_db":0.0},{"freq_hz":0.0,"message":"KC1UVP KA8HNS RRR","snr_db":0.0},{"freq_hz":0.0,"message":"CQ N9TNY EN51","snr_db":0.0},{"freq_hz":0.0,"message":"KF0TIM KQ4TCW FM14","snr_db":0.0},{"freq_hz":0.0,"message":"K9PSR AC7WY 73","snr_db":0.0},{"freq_hz":0.0,"message":"VE9NM KQ8B -08","snr_db":0.0}],"schema_version":1,"source":"ft8_lib_ffi","wav_path":"/Users/thagale/.pancetta/recordings/ft8_20260530_165043.wav","wav_sha256":"87a1061f382b6a4686c06eddf3c7c6127a10e95cebdd4268268b039919e1e15f"}