{"decodes":[{"freq_hz":0.0,"message":"N1NRL W9MO RR73","snr_db":0.0},{"freq_hz":0.0,"message":"KO3B N3LF EM66","snr_db":0.0},{"freq_hz":0.0,"message":"CQ KF9UG EN71","snr_db":0.0},{"freq_hz":0.0,"message":"VA7LWK KO3B +22","snr_db":0.0},{"freq_hz":0.0,"message":"VA7LWK AF4DN EM74","snr_db":0.0},{"freq_hz":0.0,"message":"N0SNO KF8BRC EM98","snr_db":0.0},{"freq_hz":0.0,"message":"K9DYV KF7UGV R-09","snr_db":0.0},{"freq_hz":0.0,"message":"AL6T/P KR4EZM EM80","snr_db":0.0},{"freq_hz":0.0,"message":"WB7VEQ W4IU 73","snr_db":0.0},{"freq_hz":0.0,"message":"SV9KNA KA0FMZ EM28","snr_db":0.0},{"freq_hz":0.0,"message":"CQ KD4MES EM60","snr_db":0.0},{"freq_hz":0.0,"message":"N0SNO N2TKL EM74","snr_db":0.0},{"freq_hz":0.0,"message":"KC9YTT W3BGE EM85","snr_db":0.0},{"freq_hz":0.0,"message":"N0SNO K2PS -08","snr_db":0.0},{"freq_hz":0.0,"message":"NC7I WL7E CM98","snr_db":0.0},{"freq_hz":0.0,"message":"CQ WA4TED EM75","snr_db":0.0},{"freq_hz":0.0,"message":"K7HSR KN4RNO RR73","snr_db":0.0},{"freq_hz":0.0,"message":"KC3NRA HI3QMT RR73","snr_db":0.0},{"freq_hz":0.0,"message":"CQ KQ4YIF EM17","snr_db":0.0}],"schema_version":1,"source":"ft8_lib_ffi","wav_path":"/Users/thagale/.pancetta/recordings/ft8_20260530_173458.wav","wav_sha256":"96d329fcee71eb99279cd201d3fba8228f1d454650a2b87b6a07e39eef9dcefd"}