{"decodes":[{"freq_hz":0.0,"message":"VC9UN VA3GPL FN03","snr_db":0.0},{"freq_hz":0.0,"message":"WD4W NG7E RR73","snr_db":0.0},{"freq_hz":0.0,"message":"AK6OZ KF0VUJ -16","snr_db":0.0},{"freq_hz":0.0,"message":"CQ KK4RXE EM75","snr_db":0.0},{"freq_hz":0.0,"message":"CQ N9FME EM59","snr_db":0.0},{"freq_hz":0.0,"message":"CU6AB N9MSC -11","snr_db":0.0},{"freq_hz":0.0,"message":"7Z1CE KK4ELM -16","snr_db":0.0},{"freq_hz":0.0,"message":"CQ AA3SO FN00","snr_db":0.0},{"freq_hz":0.0,"message":"CQ KC9YTT EN40","snr_db":0.0},{"freq_hz":0.0,"message":"XE2BIZ AF0E +00","snr_db":0.0},{"freq_hz":0.0,"message":"W7LCV K8BL -03","snr_db":0.0},{"freq_hz":0.0,"message":"CQ VE3OZW EN94","snr_db":0.0},{"freq_hz":0.0,"message":"N5TXL AB8MO 73","snr_db":0.0},{"freq_hz":0.0,"message":"VC9UN WV2B R+00","snr_db":0.0},{"freq_hz":0.0,"message":"KB3DQI CE3TSK -21","snr_db":0.0},{"freq_hz":0.0,"message":"A61CK N1GNB FN43","snr_db":0.0},{"freq_hz":0.0,"message":"7Z1CE AA9JC EN61","snr_db":0.0},{"freq_hz":0.0,"message":"N5SKT VP2MAA RR73","snr_db":0.0},{"freq_hz":0.0,"message":"HK0RMR W7AJE CN84","snr_db":0.0},{"freq_hz":0.0,"message":"AA4WX W7QQF R-14","snr_db":0.0},{"freq_hz":0.0,"message":"N5TXL KF8BRC EM98","snr_db":0.0}],"schema_version":1,"source":"ft8_lib_ffi","wav_path":"/Users/thagale/.pancetta/recordings/ft8_20260530_230943.wav","wav_sha256":"a63bc6faedd4d431de1e8621235e441532e85a29b49787832325862c9692fce4"}