{"decodes":[{"freq_hz":2837.5,"message":"KB9WFS W8TMB -08","snr_db":0.0,"time_sec":2.799999952316284},{"freq_hz":1900.0,"message":"KO3B N3LF EM66","snr_db":0.0,"time_sec":2.7200000286102295},{"freq_hz":396.875,"message":"CQ N4VFR EM90","snr_db":0.0,"time_sec":2.799999952316284},{"freq_hz":2725.0,"message":"N0SNO KF7UGV DN61","snr_db":0.0,"time_sec":2.7200000286102295},{"freq_hz":328.125,"message":"CQ WA4TED EM75","snr_db":0.0,"time_sec":2.7200000286102295},{"freq_hz":743.75,"message":"CQ AA9JC EN61","snr_db":0.0,"time_sec":2.3999998569488525},{"freq_hz":990.625,"message":"AD0KI KC9UR -19","snr_db":0.0,"time_sec":2.799999952316284},{"freq_hz":525.0,"message":"W4NEL KB9RP 73","snr_db":0.0,"time_sec":0.47999998927116394},{"freq_hz":950.0,"message":"NG7E WI0K 73","snr_db":0.0,"time_sec":2.6399998664855957},{"freq_hz":2456.25,"message":"KF5LHM K7CTV DM42","snr_db":0.0,"time_sec":2.879999876022339},{"freq_hz":875.0,"message":"KI5IJM KE8EOQ -14","snr_db":0.0,"time_sec":3.0399999618530273},{"freq_hz":2296.875,"message":"N5CPC K8USN EM90","snr_db":0.0,"time_sec":2.799999952316284},{"freq_hz":2565.625,"message":"KF5LHM KF9UG EN71","snr_db":0.0,"time_sec":2.879999876022339},{"freq_hz":1037.5,"message":"KF5LHM KD4CVR EM74","snr_db":0.0,"time_sec":2.7200000286102295},{"freq_hz":1590.625,"message":"W5JDB KN4RNO RR73","snr_db":0.0,"time_sec":2.7200000286102295},{"freq_hz":1762.5,"message":"CQ KP4SE FK67","snr_db":0.0,"time_sec":3.0399999618530273},{"freq_hz":584.375,"message":"CQ KF0VUJ EN42","snr_db":0.0,"time_sec":3.0399999618530273},{"freq_hz":1253.125,"message":"CQ N4NDR EM85","snr_db":0.0,"time_sec":2.7200000286102295},{"freq_hz":1971.875,"message":"KF5LHM AC7WY DN61","snr_db":0.0,"time_sec":2.7200000286102295},{"freq_hz":2884.375,"message":"VA7GEM KI7HLO -11","snr_db":0.0,"time_sec":2.799999952316284}],"schema_version":1,"source":"ft8_lib_ffi","wav_path":"/Users/thagale/.pancetta/recordings/ft8_20260530_171328.wav","wav_sha256":"a6466f60a5e0464b043e7e48adc263a71ad86a8759ced45392291ffa7eee7556"}