{"decodes":[{"freq_hz":1684.375,"message":"K4VHE KK7HSO RR73","snr_db":0.0,"time_sec":2.7200000286102295},{"freq_hz":787.5,"message":"W9RF VE9NM RR73","snr_db":0.0,"time_sec":2.7200000286102295},{"freq_hz":975.0,"message":"KF5UCO VE3XN R-07","snr_db":0.0,"time_sec":2.7200000286102295},{"freq_hz":2228.125,"message":"W0ABE WD4RCG R-11","snr_db":0.0,"time_sec":2.7200000286102295},{"freq_hz":2078.125,"message":"KO4XJ W1WCI FN42","snr_db":0.0,"time_sec":2.7200000286102295},{"freq_hz":2284.375,"message":"N3GTY KF5YRQ EM46","snr_db":0.0,"time_sec":2.879999876022339},{"freq_hz":634.375,"message":"5D4KUN NC3S -17","snr_db":0.0,"time_sec":2.799999952316284},{"freq_hz":2737.5,"message":"EG1PCS KC3OL EM28","snr_db":0.0,"time_sec":2.799999952316284},{"freq_hz":2590.625,"message":"W0HNV K3RH FN20","snr_db":0.0,"time_sec":2.799999952316284},{"freq_hz":903.125,"message":"K4WDW VA3PHP -12","snr_db":0.0,"time_sec":2.7200000286102295},{"freq_hz":2521.875,"message":"K6RDW K0JDD EN34","snr_db":0.0,"time_sec":2.7200000286102295},{"freq_hz":328.125,"message":"CQ WA4TED EM75","snr_db":0.0,"time_sec":2.6399998664855957},{"freq_hz":2818.75,"message":"US5HL W6GOK R-09","snr_db":0.0,"time_sec":2.799999952316284},{"freq_hz":1859.375,"message":"CQ KD2YQS FN20","snr_db":0.0,"time_sec":2.7200000286102295},{"freq_hz":2381.25,"message":"CQ KF9UG EN71","snr_db":0.0,"time_sec":2.7200000286102295},{"freq_hz":187.5,"message":"N0TIG K5JSG/P -14","snr_db":0.0,"time_sec":2.879999876022339},{"freq_hz":503.125,"message":"PY2UGO KG4OJT -16","snr_db":0.0,"time_sec":2.879999876022339},{"freq_hz":1981.25,"message":"K6RDW KB0TDW -18","snr_db":0.0,"time_sec":2.7200000286102295},{"freq_hz":1431.25,"message":"KC9YTT N0QX EL15","snr_db":0.0,"time_sec":2.7200000286102295},{"freq_hz":1275.0,"message":"<...> K0XU EN10","snr_db":0.0,"time_sec":2.7200000286102295},{"freq_hz":1900.0,"message":"HK0RMR N3LF EM66","snr_db":0.0,"time_sec":2.6399998664855957}],"schema_version":1,"source":"ft8_lib_ffi","wav_path":"/Users/thagale/.pancetta/recordings/ft8_20260530_213728.wav","wav_sha256":"b66c50c71a54081945f9ab0726b9849598206c365cc28bbf0ec6c71d15155c9c"}