{"decodes":[{"freq_hz":1771.875,"message":"K9ALO KK4ELM -09","snr_db":0.0,"time_sec":1.9199999570846558},{"freq_hz":1112.5,"message":"KC3HRV N2TKL EM74","snr_db":0.0,"time_sec":2.7200000286102295},{"freq_hz":518.75,"message":"KE8AFJ KJ7WLL CN85","snr_db":0.0,"time_sec":2.6399998664855957},{"freq_hz":2112.5,"message":"KF0RRJ <...> -01","snr_db":0.0,"time_sec":2.7200000286102295},{"freq_hz":928.125,"message":"KN4YBL KE8UCE 73","snr_db":0.0,"time_sec":2.7200000286102295},{"freq_hz":246.875,"message":"CQ DX KE5JTS CM98","snr_db":0.0,"time_sec":2.7200000286102295},{"freq_hz":1368.75,"message":"WA0YCN NG7E -04","snr_db":0.0,"time_sec":2.879999876022339},{"freq_hz":993.75,"message":"KE8AFJ N5KKG 73","snr_db":0.0,"time_sec":2.799999952316284},{"freq_hz":2325.0,"message":"N7WBV AC7WY DN61","snr_db":0.0,"time_sec":2.7200000286102295},{"freq_hz":1856.25,"message":"CQ POTA N0SNO","snr_db":0.0,"time_sec":2.6399998664855957},{"freq_hz":1621.875,"message":"CQ KZ4GN EL98","snr_db":0.0,"time_sec":2.4800000190734863},{"freq_hz":1931.25,"message":"KB9RP K7LNY +02","snr_db":0.0,"time_sec":2.7200000286102295},{"freq_hz":1696.875,"message":"CQ WY0V EN12","snr_db":0.0,"time_sec":2.7200000286102295},{"freq_hz":1521.875,"message":"KC9UR KQ4TCW FM14","snr_db":0.0,"time_sec":2.7200000286102295},{"freq_hz":1568.75,"message":"AI4JD WC4R FM17","snr_db":0.0,"time_sec":2.7200000286102295}],"schema_version":1,"source":"ft8_lib_ffi","wav_path":"/Users/thagale/.pancetta/recordings/ft8_20260530_171013.wav","wav_sha256":"b74af99ecbf320f63de5c76a97009103a2c9dd12c3838ff42f5781d300a235a4"}