{"decodes":[{"freq_hz":0.0,"message":"WB4RRD WA4FU RR73","snr_db":0.0},{"freq_hz":0.0,"message":"KC2NDA KJ4IHN -03","snr_db":0.0},{"freq_hz":0.0,"message":"DD1UN WA1DD R-14","snr_db":0.0},{"freq_hz":0.0,"message":"CQ NG7E DM43","snr_db":0.0},{"freq_hz":0.0,"message":"CQ K8BL EN91","snr_db":0.0},{"freq_hz":0.0,"message":"KR4GYY KI0EB +00","snr_db":0.0},{"freq_hz":0.0,"message":"N8WCR W3CDE EM73","snr_db":0.0},{"freq_hz":0.0,"message":"CQ K4OP EM77","snr_db":0.0},{"freq_hz":0.0,"message":"WD5BFH N4ZXZ -22","snr_db":0.0},{"freq_hz":0.0,"message":"OK1JXU W4OKW R-14","snr_db":0.0},{"freq_hz":0.0,"message":"K5BEK KF0U R+08","snr_db":0.0},{"freq_hz":0.0,"message":"NJ9V N5VX FM14","snr_db":0.0},{"freq_hz":0.0,"message":"<...> VE3MJM R-18","snr_db":0.0},{"freq_hz":0.0,"message":"CQ W4DJF EM86","snr_db":0.0},{"freq_hz":0.0,"message":"CQ AB9GK EN54","snr_db":0.0},{"freq_hz":0.0,"message":"AB5GC W8GAC EM79","snr_db":0.0},{"freq_hz":0.0,"message":"N1FR W0OVX 73","snr_db":0.0},{"freq_hz":0.0,"message":"HB9EFK KW8CW EM75","snr_db":0.0}],"schema_version":1,"source":"ft8_lib_ffi","wav_path":"/Users/thagale/.pancetta/recordings/ft8_20260530_205013.wav","wav_sha256":"c41791e463578a9e26e3c18dcb5a26a4cb6abbf787b772ff718f14a7f2ef2e37"}