{"decodes":[{"freq_hz":640.625,"message":"CQ KN4DS EM82","snr_db":0.0,"time_sec":2.4800000190734863},{"freq_hz":2834.375,"message":"CQ W5RWD EM26","snr_db":0.0,"time_sec":2.559999942779541},{"freq_hz":1771.875,"message":"CQ N4LOV EM63","snr_db":0.0,"time_sec":2.1599998474121094},{"freq_hz":1987.5,"message":"ER3ZW WA4TED EM75","snr_db":0.0,"time_sec":2.3999998569488525},{"freq_hz":1315.625,"message":"KF0SYD KP2BH RR73","snr_db":0.0,"time_sec":2.559999942779541},{"freq_hz":1000.0,"message":"K4TTL AA4NP 73","snr_db":0.0,"time_sec":2.4800000190734863},{"freq_hz":1396.875,"message":"KQ4YVQ KU4HO RR73","snr_db":0.0,"time_sec":2.4800000190734863},{"freq_hz":2334.375,"message":"CQ VE3ARF FN25","snr_db":0.0,"time_sec":2.3999998569488525},{"freq_hz":2443.75,"message":"XE3K WA4MB R-12","snr_db":0.0,"time_sec":2.4800000190734863},{"freq_hz":1631.25,"message":"W6KAS KT0D DM78","snr_db":0.0,"time_sec":2.4800000190734863},{"freq_hz":1450.0,"message":"CQ KD3B EM78","snr_db":0.0,"time_sec":2.3999998569488525},{"freq_hz":946.875,"message":"W2CG KE0EEY R-12","snr_db":0.0,"time_sec":2.3999998569488525},{"freq_hz":2946.875,"message":"CQ C6APS FL16","snr_db":0.0,"time_sec":2.240000009536743},{"freq_hz":1350.0,"message":"CQ KE9ZZ EN52","snr_db":0.0,"time_sec":2.0},{"freq_hz":896.875,"message":"CQ W2LOP FN30","snr_db":0.0,"time_sec":2.3999998569488525},{"freq_hz":2153.125,"message":"KO4MAQ KM4ZDM +01","snr_db":0.0,"time_sec":1.3600000143051147},{"freq_hz":1131.25,"message":"ER3ZW VE2YZX FN35","snr_db":0.0,"time_sec":2.319999933242798},{"freq_hz":350.0,"message":"IK4LZH W5RTG 73","snr_db":0.0,"time_sec":2.3999998569488525},{"freq_hz":1887.5,"message":"KT4MC ES2AJ -06","snr_db":0.0,"time_sec":1.6799999475479126},{"freq_hz":190.625,"message":"CQ CE3TSK FF46","snr_db":0.0,"time_sec":2.4800000190734863},{"freq_hz":684.375,"message":"WD8NVN WY7WL +12","snr_db":0.0,"time_sec":2.4800000190734863}],"schema_version":1,"source":"ft8_lib_ffi","wav_path":"/Users/thagale/.pancetta/recordings/ft8_20260420_022843.wav","wav_sha256":"dac2201445df10dbbd607d59adc1f0779774d23c32bca52831b036a0fb639de3"}