{"decodes":[{"freq_hz":0.0,"message":"WD4HEN AA0GD -23","snr_db":0.0},{"freq_hz":0.0,"message":"CQ KE8ESJ EM79","snr_db":0.0},{"freq_hz":0.0,"message":"K9SQ N4FJB EM63","snr_db":0.0},{"freq_hz":0.0,"message":"AF0F KE2ET EM75","snr_db":0.0},{"freq_hz":0.0,"message":"KA5RBZ N4ARZ EM84","snr_db":0.0},{"freq_hz":0.0,"message":"CQ KG4OJT FM18","snr_db":0.0},{"freq_hz":0.0,"message":"KZ4GN W8ASH 73","snr_db":0.0},{"freq_hz":0.0,"message":"CQ POTA K9DY EM69","snr_db":0.0},{"freq_hz":0.0,"message":"F4DIA N2UD EL87","snr_db":0.0},{"freq_hz":0.0,"message":"AB8PS NR6TT 73","snr_db":0.0},{"freq_hz":0.0,"message":"CQ VE9NM FN65","snr_db":0.0},{"freq_hz":0.0,"message":"<...> WB8TLI EN70","snr_db":0.0},{"freq_hz":0.0,"message":"N4DWD W4NEL RR73","snr_db":0.0},{"freq_hz":0.0,"message":"KF0TNR KN4RNO RR73","snr_db":0.0},{"freq_hz":0.0,"message":"K0VJD KE8IFR R-19","snr_db":0.0},{"freq_hz":0.0,"message":"KG5FI WA0TDA +00","snr_db":0.0},{"freq_hz":0.0,"message":"WB0PTD KK7O R+16","snr_db":0.0},{"freq_hz":0.0,"message":"K7NGS KO6MFA +08","snr_db":0.0}],"schema_version":1,"source":"ft8_lib_ffi","wav_path":"/Users/thagale/.pancetta/recordings/ft8_20260530_155428.wav","wav_sha256":"f8a4b7187ff17256c76d7226f2a2bcbfb6e5e3daee11f9aca6e3aabca01b4568"}